fts3/__init__.py
fts3/cli/__init__.py
fts3/cli/banning.py
fts3/cli/base.py
fts3/cli/delegator.py
fts3/cli/jobcanceller.py
fts3/cli/jobdeletionsubmitter.py
fts3/cli/joblister.py
fts3/cli/jobshower.py
fts3/cli/jobsubmitter.py
fts3/cli/serverstatus.py
fts3/cli/utils.py
fts3/cli/whoami.py
fts3/rest/__init__.py
fts3/rest/client/__init__.py
fts3/rest/client/ban.py
fts3/rest/client/context.py
fts3/rest/client/delegator.py
fts3/rest/client/exceptions.py
fts3/rest/client/inquirer.py
fts3/rest/client/request.py
fts3/rest/client/submitter.py
fts3/rest/client/easy/__init__.py
fts3/rest/client/easy/ban.py
fts3/rest/client/easy/delegate.py
fts3/rest/client/easy/state.py
fts3/rest/client/easy/submission.py
fts3/rest/client/easy/whoami.py
fts3-3.14.2.data/scripts/fts-rest-ban
fts3-3.14.2.data/scripts/fts-rest-delegate
fts3-3.14.2.data/scripts/fts-rest-delete-submit
fts3-3.14.2.data/scripts/fts-rest-server-status
fts3-3.14.2.data/scripts/fts-rest-transfer-cancel
fts3-3.14.2.data/scripts/fts-rest-transfer-list
fts3-3.14.2.data/scripts/fts-rest-transfer-status
fts3-3.14.2.data/scripts/fts-rest-transfer-submit
fts3-3.14.2.data/scripts/fts-rest-whoami
fts3-3.14.2.dist-info/LICENSE
fts3-3.14.2.dist-info/METADATA
fts3-3.14.2.dist-info/WHEEL
fts3-3.14.2.dist-info/top_level.txt
fts3-3.14.2.dist-info/RECORD
