Metadata-Version: 2.1
Name: fts3
Version: 3.14.2
Summary: FTS Python3 CLI and libraries
Home-page: https://gitlab.cern.ch/fts/fts-rest-flask
Author: CERN -- FTS team
Author-email: fts-devel@cern.ch
License: Apache License 2.0
Platform: UNKNOWN
Classifier: Development Status :: 5 - Production/Stable
Classifier: Environment :: Console
Classifier: License :: OSI Approved :: Apache Software License
Classifier: Operating System :: POSIX :: Linux
Classifier: Programming Language :: Python :: 3.9
Classifier: Programming Language :: Python :: 3.10
Classifier: Programming Language :: Python :: 3.11
Requires-Python: >=3.9
License-File: LICENSE
Requires-Dist: M2Crypto
Requires-Dist: requests
Requires-Dist: setuptools (>=39)
